Workbook

Sheet Orders by Status
A3: Row Labels | B3: Count of OrderID
A4: Cancelled | B4: 250
A5: Delivered | B5: 231
A6: Pending | B6: 237
A7: Returned | B7: 247
A8: Shipped | B8: 235
A9: Grand Total | B9: 1200

Sheet Revenue by Product
A3: Row Labels | B3: Sum of TotalPrice
A4: Chair | B4: 195620.11
A5: Desk | B5: 167459.93
A6: Laptop | B6: 192126.56
A7: Monitor | B7: 175651.41
A8: Phone | B8: 151722.39
A9: Printer | B9: 195612.61
A10: Tablet | B10: 186568.95
A11: Grand Total | B11: 1264762

Sheet Revenue by Referral Source
A3: Row Labels | B3: Sum of TotalPrice
A4: Email | B4: 261808.55
A5: Facebook | B5: 250410.9
A6: Google | B6: 250441.48
A7: Instagram | B7: 275285.45
A8: Referral | B8: 226815.58
A9: Grand Total | B9: 1264762

Sheet Average Order Value by Payment
A3: Row Labels | B3: Average of TotalPrice
A4: Cash | B4: 1056.0418
A5: Credit Card | B5: 1127.554
A6: Debit Card | B6: 1001.5568
A7: Gift Card | B7: 1070.9736
A8: Online | B8: 1017.2207
A9: Grand Total | B9: 1053.9683

Sheet Revenue by Month
A3: Row Labels | B3: Sum of TotalPrice
A4: 2023 | B4: 552643.24
A5: Jan | B5: 56685.75
A6: Feb | B6: 40117.66
A7: Mar | B7: 48609.37
A8: Apr | B8: 27751.71
A9: May | B9: 63836.84
A10: Jun | B10: 49500.19
A11: Jul | B11: 42820.66
A12: Aug | B12: 54352.14
A13: Sep | B13: 29526.67
A14: Oct | B14: 52607.85
A15: Nov | B15: 43079.67
... A37: Grand Total | B37: 1264762

Sheet EDA
A1: Quantity | C1: Unit Price | E1: Total Price | G1: Lower Bound | H1: =_xlfn.QUARTILE.INC('[1]Cleaned Data set'!N2:N1201,1)-1.5*(_xlfn.QUARTILE.INC('[1]Cleaned Data set'!N2:N1201,3)-_xlfn.QUARTILE.INC('[1]Cleaned Data set'!N2:N1201,1)) -> -1341.4125 | I1: Corr: Quantity vs UnitPrice | J1: =CORREL('[1]Cleaned Data set'!E2:E1201,'[1]Cleaned Data set'!F2:F1201) -> 0.014553341
G2: Upper Bound | H2: =_xlfn.QUARTILE.INC('[1]Cleaned Data set'!N2:N1201,3)+1.5*(_xlfn.QUARTILE.INC('[1]Cleaned Data set'!N2:N1201,3)-_xlfn.QUARTILE.INC('[1]Cleaned Data set'!N2:N1201,1)) -> 3330.4075 | I2: Corr: UnitPrice vs TotalPrice | J2: =CORREL('[1]Cleaned Data set'!F2:F1201,'[1]Cleaned Data set'!N2:N1201) -> 0.71708109
A3: Mean | B3: 2.9458333 | C3: Mean | D3: 356.41275 | E3: Mean | F3: 1053.9683 | I3: Corr: Quantity vs TotalPrice | J3: =CORREL('[1]Cleaned Data set'!E2:E1201,'[1]Cleaned Data set'!N2:N1201) -> 0.61525136
A4: Standard Error | B4: 0.040632673 | C4: Standard Error | D4: 5.6920139 | E4: Standard Error | F4: 23.66722
A5: Median | B5: 3 | C5: Median | D5: 364.21 | E5: Median | F5: 823.615
A6: Mode | B6: 1 | C6: Mode | D6: 127.18 | E6: Mode | F6: 635.9
A7: Standard Deviation | B7: 1.4075571 | C7: Standard Deviation | D7: 197.17715 | E7: Standard Deviation | F7: 819.85656
A8: Sample Variance | B8: 1.981217 | C8: Sample Variance | D8: 38878.827 | E8: Sample Variance | F8: 672164.78
A9: Kurtosis | B9: -1.2945959 | C9: Kurtosis | D9: -1.1910109 | E9: Kurtosis | F9: -0.040414717
A10: Skewness | B10: 0.027922314 | C10: Skewness | D10: -0.026511641 | E10: Skewness | F10: 0.89135908
A11: Range | B11: 4 | C11: Range | D11: 688.54 | E11: Range | F11: 3445.01
A12: Minimum | B12: 1 | C12: Minimum | D12: 11.39 | E12: Minimum | F12: 11.39
A13: Maximum | B13: 5 | C13: Maximum | D13: 699.93 | E13: Maximum | F13: 3456.4
A14: Sum | B14: 3535 | C14: Sum | D14: 427695.3 | E14: Sum | F14: 1264762
A15: Count | B15: 1200 | C15: Count | D15: 1200 | E15: Count | F15: 1200
A16: Confidence Level(95.0%) | B16: 0.07971905 | C16: Confidence Level(95.0%) | D16: 11.167415 | E16: Confidence Level(95.0%) | F16: 46.433772

Sheet Cleaned Data set
A1: OrderID | B1: Date | C1: CustomerID | D1: Product | E1: Quantity | F1: UnitPrice | G1: ShippingAddress | H1: PaymentMethod | I1: OrderStatus | J1: TrackingNumber | K1: ItemsInCart | L1: CouponCode | M1: ReferralSource | N1: TotalPrice | O1: CouponCode_Cleaned | P1: Outlier Flag
A2: ORD200000 | B2: 44930 | C2: C72649 | D2: Monitor | E2: 5 | F2: 570.62 | G2: 928 Main St | H2: Debit Card | I2: Shipped | J2: TRK37947903 | K2: 7 | L2: SAVE10 | M2: Instagram | N2: 2853.1 | O2: =IF(L2="","No Coupon",L2) -> SAVE10 | P2: =IF(OR(N2<EDA!$H$1,N2>EDA!$H$2),"Outlier","Normal") -> Normal
A3: ORD200001 | B3: 45527 | C3: C75739 | D3: Phone | E3: 2 | F3: 151.35 | G3: 823 Main St | H3: Online | I3: Shipped | J3: TRK91186779 | K3: 3 | L3: SAVE10 | M3: Referral | N3: 302.7 | O3: =IF(L3="","No Coupon",L3) -> SAVE10 | P3: =IF(OR(N3<EDA!$H$1,N3>EDA!$H$2),"Outlier","Normal") -> Normal
A4: ORD200002 | B4: 45349 | C4: C81728 | D4: Tablet | E4: 5 | F4: 550.68 | G4: 512 Main St | H4: Credit Card | I4: Cancelled | J4: TRK42903982 | K4: 8 | L4: FREESHIP | M4: Email | N4: 2753.4 | O4: =IF(L4="","No Coupon",L4) -> FREESHIP | P4: =IF(OR(N4<EDA!$H$1,N4>EDA!$H$2),"Outlier","Normal") -> Normal
A5: ORD200003 | B5: 45214 | C5: C33540 | D5: Chair | E5: 1 | F5: 273.19 | G5: 275 Main St | H5: Debit Card | I5: Returned | J5: TRK62788070 | K5: 5 | L5: SAVE10 | M5: Facebook | N5: 273.19 | O5: =IF(L5="","No Coupon",L5) -> SAVE10 | P5: =IF(OR(N5<EDA!$H$1,N5>EDA!$H$2),"Outlier","Normal") -> Normal
A6: ORD200004 | B6: 45785 | C6: C81840 | D6: Printer | E6: 4 | F6: 626.01 | G6: 668 Main St | H6: Online | I6: Delivered | J6: TRK29241424 | K6: 8 | L6: SAVE10 | M6: Email | N6: 2504.04 | O6: =IF(L6="","No Coupon",L6) -> SAVE10 | P6: =IF(OR(N6<EDA!$H$1,N6>EDA!$H$2),"Outlier","Normal") -> Normal
A7: ORD200005 | B7: 45222 | C7: C37249 | D7: Phone | E7: 2 | F7: 245.86 | G7: 934 Main St | H7: Credit Card | I7: Shipped | J7: TRK72976927 | K7: 4 | L7: SAVE10 | M7: Instagram | N7: 491.72 | O7: =IF(L7="","No Coupon",L7) -> SAVE10 | P7: =IF(OR(N7<EDA!$H$1,N7>EDA!$H$2),"Outlier","Normal") -> Normal
A8: ORD200006 | B8: 45825 | C8: C83492 | D8: Laptop | E8: 1 | F8: 664.42 | G8: 986 Main St | H8: Gift Card | I8: Returned | J8: TRK96417362 | K8: 6 | L8: SAVE10 | M8: Facebook | N8: 664.42 | O8: =IF(L8="","No Coupon",L8) -> SAVE10 | P8: =IF(OR(N8<EDA!$H$1,N8>EDA!$H$2),"Outlier","Normal") -> Normal
A9: ORD200007 | B9: 45058 | C9: C41460 | D9: Monitor | E9: 5 | F9: 149.55 | G9: 706 Main St | H9: Cash | I9: Shipped | J9: TRK78809193 | K9: 9 | L9: FREESHIP | M9: Facebook | N9: 747.75 | O9: =IF(L9="","No Coupon",L9) -> FREESHIP | P9: =IF(OR(N9<EDA!$H$1,N9>EDA!$H$2),"Outlier","Normal") -> Normal
A10: ORD200008 | B10: 45749 | C10: C26817 | D10: Phone | E10: 2 | F10: 134.28 | G10: 904 Main St | H10: Gift Card | I10: Cancelled | J10: TRK61042692 | K10: 2 | M10: Email | N10: 268.56 | O10: =IF(L10="","No Coupon",L10) -> No Coupon | P10: =IF(OR(N10<EDA!$H$1,N10>EDA!$H$2),"Outlier","Normal") -> Normal
A11: ORD200009 | B11: 45251 | C11: C31946 | D11: Desk | E11: 4 | F11: 509.38 | G11: 102 Main St | H11: Credit Card | I11: Shipped | J11: TRK33478363 | K11: 6 | L11: SAVE10 | M11: Google | N11: 2037.52 | O11: =IF(L11="","No Coupon",L11) -> SAVE10 | P11: =IF(OR(N11<EDA!$H$1,N11>EDA!$H$2),"Outlier","Normal") -> Normal
A12: ORD200010 | B12: 45289 | C12: C43443 | D12: Tablet | E12: 5 | F12: 625.97 | G12: 333 Main St | H12: Credit Card | I12: Returned | J12: TRK98859248 | K12: 9 | L12: WINTER15 | M12: Instagram | N12: 3129.85 | O12: =IF(L12="","No Coupon",L12) -> WINTER15 | P12: =IF(OR(N12<EDA!$H$1,N12>EDA!$H$2),"Outlier","Normal") -> Normal
A13: ORD200011 | B13: 45339 | C13: C93861 | D13: Monitor | E13: 3 | F13: 49.14 | G13: 831 Main St | H13: Online | I13: Returned | J13: TRK48234646 | K13: 7 | L13: SAVE10 | M13: Email | N13: 147.42 | O13: =IF(L13="","No Coupon",L13) -> SAVE10 | P13: =IF(OR(N13<EDA!$H$1,N13>EDA!$H$2),"Outlier","Normal") -> Normal
A14: ORD200012 | B14: 45580 | C14: C38785 | D14: Monitor | E14: 2 | F14: 180.5 | G14: 179 Main St | H14: Debit Card | I14: Pending | J14: TRK20419991 | K14: 6 | L14: FREESHIP | M14: Referral | N14: 361 | O14: =IF(L14="","No Coupon",L14) -> FREESHIP | P14: =IF(OR(N14<EDA!$H$1,N14>EDA!$H$2),"Outlier","Normal") -> Normal
A15: ORD200013 | B15: 45168 | C15: C88348 | D15: Laptop | E15: 3 | F15: 201.49 | G15: 903 Main St | H15: Credit Card | I15: Returned | J15: TRK81913874 | K15: 4 | L15: FREESHIP | M15: Facebook | N15: 604.47 | O15: =IF(L15="","No Coupon",L15) -> FREESHIP | P15: =IF(OR(N15<EDA!$H$1,N15>EDA!$H$2),"Outlier","Normal") -> Normal
A16: ORD200014 | B16: 45012 | C16: C98474 | D16: Tablet | E16: 2 | F16: 393.33 | G16: 980 Main St | H16: Debit Card | I16: Pending | J16: TRK79186539 | K16: 3 | L16: SAVE10 | M16: Instagram | N16: 786.66 | O16: =IF(L16="","No Coupon",L16) -> SAVE10 | P16: =IF(OR(N16<EDA!$H$1,N16>EDA!$H$2),"Outlier","Normal") -> Normal
A17: ORD200015 | B17: 45124 | C17: C39416 | D17: Printer | E17: 1 | F17: 473.96 | G17: 942 Main St | H17: Cash | I17: Delivered | J17: TRK54930938 | K17: 3 | M17: Google | N17: 473.96 | O17: =IF(L17="","No Coupon",L17) -> No Coupon | P17: =IF(OR(N17<EDA!$H$1,N17>EDA!$H$2),"Outlier","Normal") -> Normal
A18: ORD200016 | B18: 44950 | C18: C28976 | D18: Printer | E18: 2 | F18: 533.81 | G18: 914 Main St | H18: Credit Card | I18: Pending | J18: TRK13194259 | K18: 3 | L18: FREESHIP | M18: Email | N18: 1067.62 | O18: =IF(L18="","No Coupon",L18) -> FREESHIP | P18: =IF(OR(N18<EDA!$H$1,N18>EDA!$H$2),"Outlier","Normal") -> Normal
A19: ORD200017 | B19: 45353 | C19: C60672 | D19: Tablet | E19: 1 | F19: 423.4 | G19: 382 Main St | H19: Debit Card | I19: Shipped | J19: TRK11972116 | K19: 3 | M19: Referral | N19: 423.4 | O19: =IF(L19="","No Coupon",L19) -> No Coupon | P19: =IF(OR(N19<EDA!$H$1,N19>EDA!$H$2),"Outlier","Normal") -> Normal
A20: ORD200018 | B20: 45742 | C20: C84329 | D20: Desk | E20: 1 | F20: 431.44 | G20: 891 Main St | H20: Gift Card | I20: Pending | J20: TRK65191045 | K20: 3 | L20: SAVE10 | M20: Facebook | N20: 431.44 | O20: =IF(L20="","No Coupon",L20) -> SAVE10 | P20: =IF(OR(N20<EDA!$H$1,N20>EDA!$H$2),"Outlier","Normal") -> Normal
A21: ORD200019 | B21: 44949 | C21: C14552 | D21: Monitor | E21: 5 | F21: 224 | G21: 273 Main St | H21: Cash | I21: Returned | J21: TRK59101365 | K21: 9 | L21: SAVE10 | M21: Google | N21: 1120 | O21: =IF(L21="","No Coupon",L21) -> SAVE10 | P21: =IF(OR(N21<EDA!$H$1,N21>EDA!$H$2),"Outlier","Normal") -> Normal
A22: ORD200020 | B22: 45054 | C22: C54829 | D22: Chair | E22: 5 | F22: 62.51 | G22: 587 Main St | H22: Cash | I22: Pending | J22: TRK16718651 | K22: 9 | L22: WINTER15 | M22: Instagram | N22: 312.55 | O22: =IF(L22="","No Coupon",L22) -> WINTER15 | P22: =IF(OR(N22<EDA!$H$1,N22>EDA!$H$2),"Outlier","Normal") -> Normal
A23: ORD200021 | B23: 45613 | C23: C99023 | D23: Monitor | E23: 4 | F23: 342.95 | G23: 569 Main St | H23: Cash | I23: Delivered | J23: TRK52646983 | K23: 6 | M23: Google | N23: 1371.8 | O23: =IF(L23="","No Coupon",L23) -> No Coupon | P23: =IF(OR(N23<EDA!$H$1,N23>EDA!$H$2),"Outlier","Normal") -> Normal
A24: ORD200022 | B24: 44955 | C24: C34416 | D24: Monitor | E24: 2 | F24: 49.62 | G24: 633 Main St | H24: Online | I24: Pending | J24: TRK75937350 | K24: 2 | L24: SAVE10 | M24: Google | N24: 99.24 | O24: =IF(L24="","No Coupon",L24) -> SAVE10 | P24: =IF(OR(N24<EDA!$H$1,N24>EDA!$H$2),"Outlier","Normal") -> Normal
A25: ORD200023 | B25: 45756 | C25: C42372 | D25: Phone | E25: 4 | F25: 273.25 | G25: 755 Main St | H25: Debit Card | I25: Cancelled | J25: TRK36168083 | K25: 5 | L25: FREESHIP | M25: Referral | N25: 1093 | O25: =IF(L25="","No Coupon",L25) -> FREESHIP | P25: =IF(OR(N25<EDA!$H$1,N25>EDA!$H$2),"Outlier","Normal") -> Normal
A26: ORD200024 | B26: 45595 | C26: C17470 | D26: Laptop | E26: 2 | F26: 230.95 | G26: 956 Main St | H26: Online | I26: Delivered | J26: TRK28775057 | K26: 3 | L26: WINTER15 | M26: Referral | N26: 461.9 | O26: =IF(L26="","No Coupon",L26) -> WINTER15 | P26: =IF(OR(N26<EDA!$H$1,N26>EDA!$H$2),"Outlier","Normal") -> Normal
A27: ORD200025 | B27: 45497 | C27: C42577 | D27: Monitor | E27: 1 | F27: 399.98 | G27: 709 Main St | H27: Debit Card | I27: Delivered | J27: TRK69423327 | K27: 3 | L27: WINTER15 | M27: Email | N27: 399.98 | O27: =IF(L27="","No Coupon",L27) -> WINTER15 | P27: =IF(OR(N27<EDA!$H$1,N27>EDA!$H$2),"Outlier","Normal") -> Normal
A28: ORD200026 | B28: 45357 | C28: C21944 | D28: Laptop | E28: 5 | F28: 59.55 | G28: 296 Main St | H28: Online | I28: Delivered | J28: TRK80276812 | K28: 6 | M28: Referral | N28: 297.75 | O28: =IF(L28="","No Coupon",L28) -> No Coupon | P28: =IF(OR(N28<EDA!$H$1,N28>EDA!$H$2),"Outlier","Normal") -> Normal
A29: ORD200027 | B29: 45344 | C29: C97593 | D29: Printer | E29: 1 | F29: 472.74 | G29: 881 Main St | H29: Online | I29: Shipped | J29: TRK89117573 | K29: 6 | L29: WINTER15 | M29: Google | N29: 472.74 | O29: =IF(L29="","No Coupon",L29) -> WINTER15 | P29: =IF(OR(N29<EDA!$H$1,N29>EDA!$H$2),"Outlier","Normal") -> Normal
A30: ORD200028 | B30: 45251 | C30: C59823 | D30: Phone | E30: 4 | F30: 160.07 | G30: 568 Main St | H30: Online | I30: Pending | J30: TRK65895539 | K30: 5 | M30: Email | N30: 640.28 | O30: =IF(L30="","No Coupon",L30) -> No Coupon | P30: =IF(OR(N30<EDA!$H$1,N30>EDA!$H$2),"Outlier","Normal") -> Normal
A31: ORD200029 | B31: 45555 | C31: C33260 | D31: Desk | E31: 3 | F31: 423.53 | G31: 930 Main St | H31: Credit Card | I31: Delivered | J31: TRK59744090 | K31: 6 | L31: SAVE10 | M31: Referral | N31: 1270.59 | O31: =IF(L31="","No Coupon",L31) -> SAVE10 | P31: =IF(OR(N31<EDA!$H$1,N31>EDA!$H$2),"Outlier","Normal") -> Normal
A32: ORD200030 | B32: 45738 | C32: C44267 | D32: Monitor | E32: 2 | F32: 426.7 | G32: 895 Main St | H32: Online | I32: Pending | J32: TRK54751444 | K32: 5 | L32: SAVE10 | M32: Referral | N32: 853.4 | O32: =IF(L32="","No Coupon",L32) -> SAVE10 | P32: =IF(OR(N32<EDA!$H$1,N32>EDA!$H$2),"Outlier","Normal") -> Normal
A33: ORD200031 | B33: 45107 | C33: C26445 | D33: Chair | E33: 3 | F33: 500.08 | G33: 996 Main St | H33: Debit Card | I33: Returned | J33: TRK31229981 | K33: 6 | M33: Facebook | N33: 1500.24 | O33: =IF(L33="","No Coupon",L33) -> No Coupon | P33: =IF(OR(N33<EDA!$H$1,N33>EDA!$H$2),"Outlier","Normal") -> Normal
A34: ORD200032 | B34: 45047 | C34: C12388 | D34: Tablet | E34: 5 | F34: 536.72 | G34: 830 Main St | H34: Cash | I34: Delivered | J34: TRK99261395 | K34: 10 | M34: Email | N34: 2683.6 | O34: =IF(L34="","No Coupon",L34) -> No Coupon | P34: =IF(OR(N34<EDA!$H$1,N34>EDA!$H$2),"Outlier","Normal") -> Normal
A35: ORD200033 | B35: 45082 | C35: C52184 | D35: Chair | E35: 1 | F35: 162.77 | G35: 912 Main St | H35: Online | I35: Cancelled | J35: TRK73312471 | K35: 4 | L35: WINTER15 | M35: Facebook | N35: 162.77 | O35: =IF(L35="","No Coupon",L35) -> WINTER15 | P35: =IF(OR(N35<EDA!$H$1,N35>EDA!$H$2),"Outlier","Normal") -> Normal
A36: ORD200034 | B36: 44933 | C36: C67195 | D36: Chair | E36: 4 | F36: 576.52 | G36: 926 Main St | H36: Credit Card | I36: Pending | J36: TRK55467915 | K36: 5 | L36: WINTER15 | M36: Facebook | N36: 2306.08 | O36: =IF(L36="","No Coupon",L36) -> WINTER15 | P36: =IF(OR(N36<EDA!$H$1,N36>EDA!$H$2),"Outlier","Normal") -> Normal
A37: ORD200035 | B37: 45633 | C37: C50304 | D37: Monitor | E37: 2 | F37: 465.15 | G37: 128 Main St | H37: Online | I37: Shipped | J37: TRK46850888 | K37: 2 | L37: SAVE10 | M37: Facebook | N37: 930.3 | O37: =IF(L37="","No Coupon",L37) -> SAVE10 | P37: =IF(OR(N37<EDA!$H$1,N37>EDA!$H$2),"Outlier","Normal") -> Normal
A38: ORD200036 | B38: 45785 | C38: C59337 | D38: Laptop | E38: 2 | F38: 534.43 | G38: 465 Main St | H38: Debit Card | I38: Pending | J38: TRK50961250 | K38: 5 | M38: Facebook | N38: 1068.86 | O38: =IF(L38="","No Coupon",L38) -> No Coupon | P38: =IF(OR(N38<EDA!$H$1,N38>EDA!$H$2),"Outlier","Normal") -> Normal
A39: ORD200037 | B39: 45579 | C39: C10054 | D39: Laptop | E39: 2 | F39: 76.74 | G39: 409 Main St | H39: Cash | I39: Returned | J39: TRK94005261 | K39: 7 | L39: SAVE10 | M39: Instagram | N39: 153.48 | O39: =IF(L39="","No Coupon",L39) -> SAVE10 | P39: =IF(OR(N39<EDA!$H$1,N39>EDA!$H$2),"Outlier","Normal") -> Normal
A40: ORD200038 | B40: 45645 | C40: C15924 | D40: Laptop | E40: 1 | F40: 245.89 | G40: 549 Main St | H40: Debit Card | I40: Delivered | J40: TRK14835975 | K40: 3 | L40: SAVE10 | M40: Google | N40: 245.89 | O40: =IF(L40="","No Coupon",L40) -> SAVE10 | P40: =IF(OR(N40<EDA!$H$1,N40>EDA!$H$2),"Outlier","Normal") -> Normal
A41: ORD200039 | B41: 45715 | C41: C96664 | D41: Printer | E41: 3 | F41: 256.46 | G41: 666 Main St | H41: Credit Card | I41: Delivered | J41: TRK85508960 | K41: 4 | L41: SAVE10 | M41: Referral | N41: 769.38 | O41: =IF(L41="","No Coupon",L41) -> SAVE10 | P41: =IF(OR(N41<EDA!$H$1,N41>EDA!$H$2),"Outlier","Normal") -> Normal
A42: ORD200040 | B42: 45158 | C42: C84766 | D42: Desk | E42: 2 | F42: 344.02 | G42: 267 Main St | H42: Online | I42: Delivered | J42: TRK78967923 | K42: 4 | L42: FREESHIP | M42: Instagram | N42: 688.04 | O42: =IF(L42="","No Coupon",L42) -> FREESHIP | P42: =IF(OR(N42<EDA!$H$1,N42>EDA!$H$2),"Outlier","Normal") -> Normal
A43: ORD200041 | B43: 45265 | C43: C20212 | D43: Monitor | E43: 3 | F43: 611.45 | G43: 657 Main St | H43: Gift Card | I43: Pending | J43: TRK69733327 | K43: 4 | L43: FREESHIP | M43: Instagram | N43: 1834.35 | O43: =IF(L43="","No Coupon",L43) -> FREESHIP | P43: =IF(OR(N43<EDA!$H$1,N43>EDA!$H$2),"Outlier","Normal") -> Normal
A44: ORD200042 | B44: 45418 | C44: C28712 | D44: Printer | E44: 2 | F44: 151.66 | G44: 980 Main St | H44: Cash | I44: Cancelled | J44: TRK40772558 | K44: 6 | M44: Instagram | N44: 303.32 | O44: =IF(L44="","No Coupon",L44) -> No Coupon | P44: =IF(OR(N44<EDA!$H$1,N44>EDA!$H$2),"Outlier","Normal") -> Normal
A45: ORD200043 | B45: 45274 | C45: C60572 | D45: Chair | E45: 3 | F45: 499.21 | G45: 871 Main St | H45: Online | I45: Cancelled | J45: TRK20351666 | K45: 8 | M45: Instagram | N45: 1497.63 | O45: =IF(L45="","No Coupon",L45) -> No Coupon | P45: =IF(OR(N45<EDA!$H$1,N45>EDA!$H$2),"Outlier","Normal") -> Normal
A46: ORD200044 | B46: 45768 | C46: C73225 | D46: Phone | E46: 2 | F46: 550.18 | G46: 996 Main St | H46: Gift Card | I46: Returned | J46: TRK73848522 | K46: 3 | L46: FREESHIP | M46: Referral | N46: 1100.36 | O46: =IF(L46="","No Coupon",L46) -> FREESHIP | P46: =IF(OR(N46<EDA!$H$1,N46>EDA!$H$2),"Outlier","Normal") -> Normal
A47: ORD200045 | B47: 45332 | C47: C17388 | D47: Chair | E47: 1 | F47: 317.25 | G47: 157 Main St | H47: Debit Card | I47: Returned | J47: TRK47077395 | K47: 1 | L47: SAVE10 | M47: Facebook | N47: 317.25 | O47: =IF(L47="","No Coupon",L47) -> SAVE10 | P47: =IF(OR(N47<EDA!$H$1,N47>EDA!$H$2),"Outlier","Normal") -> Normal
A48: ORD200046 | B48: 45469 | C48: C43212 | D48: Monitor | E48: 4 | F48: 550.14 | G48: 223 Main St | H48: Debit Card | I48: Pending | J48: TRK25100762 | K48: 4 | L48: FREESHIP | M48: Instagram | N48: 2200.56 | O48: =IF(L48="","No Coupon",L48) -> FREESHIP | P48: =IF(OR(N48<EDA!$H$1,N48>EDA!$H$2),"Outlier","Normal") -> Normal
A49: ORD200047 | B49: 45126 | C49: C38134 | D49: Desk | E49: 2 | F49: 209.94 | G49: 323 Main St | H49: Credit Card | I49: Returned | J49: TRK42450754 | K49: 3 | L49: FREESHIP | M49: Email | N49: 419.88 | O49: =IF(L49="","No Coupon",L49) -> FREESHIP | P49: =IF(OR(N49<EDA!$H$1,N49>EDA!$H$2),"Outlier","Normal") -> Normal
A50: ORD200048 | B50: 45164 | C50: C12408 | D50: Monitor | E50: 2 | F50: 80.77 | G50: 464 Main St | H50: Debit Card | I50: Shipped | J50: TRK38938858 | K50: 4 | M50: Google | N50: 161.54 | O50: =IF(L50="","No Coupon",L50) -> No Coupon | P50: =IF(OR(N50<EDA!$H$1,N50>EDA!$H$2),"Outlier","Normal") -> Normal
A51: ORD200049 | B51: 45206 | C51: C11985 | D51: Printer | E51: 1 | F51: 30.44 | G51: 633 Main St | H51: Credit Card | I51: Shipped | J51: TRK53272402 | K51: 1 | L51: SAVE10 | M51: Email | N51: 30.44 | O51: =IF(L51="","No Coupon",L51) -> SAVE10 | P51: =IF(OR(N51<EDA!$H$1,N51>EDA!$H$2),"Outlier","Normal") -> Normal
A52: ORD200050 | B52: 45138 | C52: C96494 | D52: Tablet | E52: 1 | F52: 179.22 | G52: 446 Main St | H52: Online | I52: Cancelled | J52: TRK14675049 | K52: 6 | L52: FREESHIP | M52: Instagram | N52: 179.22 | O52: =IF(L52="","No Coupon",L52) -> FREESHIP | P52: =IF(OR(N52<EDA!$H$1,N52>EDA!$H$2),"Outlier","Normal") -> Normal
A53: ORD200051 | B53: 45656 | C53: C36778 | D53: Tablet | E53: 1 | F53: 388.33 | G53: 434 Main St | H53: Cash | I53: Returned | J53: TRK67610289 | K53: 2 | L53: SAVE10 | M53: Facebook | N53: 388.33 | O53: =IF(L53="","No Coupon",L53) -> SAVE10 | P53: =IF(OR(N53<EDA!$H$1,N53>EDA!$H$2),"Outlier","Normal") -> Normal
A54: ORD200052 | B54: 45543 | C54: C30513 | D54: Tablet | E54: 1 | F54: 586.44 | G54: 232 Main St | H54: Online | I54: Returned | J54: TRK64320429 | K54: 5 | L54: SAVE10 | M54: Facebook | N54: 586.44 | O54: =IF(L54="","No Coupon",L54) -> SAVE10 | P54: =IF(OR(N54<EDA!$H$1,N54>EDA!$H$2),"Outlier","Normal") -> Normal
A55: ORD200053 | B55: 45430 | C55: C67551 | D55: Phone | E55: 4 | F55: 488.78 | G55: 512 Main St | H55: Online | I55: Returned | J55: TRK94992552 | K55: 5 | L55: FREESHIP | M55: Google | N55: 1955.12 | O55: =IF(L55="","No Coupon",L55) -> FREESHIP | P55: =IF(OR(N55<EDA!$H$1,N55>EDA!$H$2),"Outlier","Normal") -> Normal
A56: ORD200054 | B56: 45743 | C56: C48120 | D56: Chair | E56: 1 | F56: 280.25 | G56: 623 Main St | H56: Online | I56: Pending | J56: TRK11014449 | K56: 5 | L56: WINTER15 | M56: Email | N56: 280.25 | O56: =IF(L56="","No Coupon",L56) -> WINTER15 | P56: =IF(OR(N56<EDA!$H$1,N56>EDA!$H$2),"Outlier","Normal") -> Normal
A57: ORD200055 | B57: 45832 | C57: C95984 | D57: Printer | E57: 3 | F57: 344.4 | G57: 565 Main St | H57: Online | I57: Cancelled | J57: TRK67434829 | K57: 3 | M57: Facebook | N57: 1033.2 | O57: =IF(L57="","No Coupon",L57) -> No Coupon | P57: =IF(OR(N57<EDA!$H$1,N57>EDA!$H$2),"Outlier","Normal") -> Normal
A58: ORD200056 | B58: 45067 | C58: C54298 | D58: Tablet | E58: 3 | F58: 479.21 | G58: 566 Main St | H58: Cash | I58: Cancelled | J58: TRK62902341 | K58: 5 | L58: WINTER15 | M58: Referral | N58: 1437.63 | O58: =IF(L58="","No Coupon",L58) -> WINTER15 | P58: =IF(OR(N58<EDA!$H$1,N58>EDA!$H$2),"Outlier","Normal") -> Normal
A59: ORD200057 | B59: 44948 | C59: C88036 | D59: Printer | E59: 5 | F59: 314.27 | G59: 842 Main St | H59: Cash | I59: Returned | J59: TRK52470128 | K59: 6 | L59: SAVE10 | M59: Instagram | N59: 1571.35 | O59: =IF(L59="","No Coupon",L59) -> SAVE10 | P59: =IF(OR(N59<EDA!$H$1,N59>EDA!$H$2),"Outlier","Normal") -> Normal
A60: ORD200058 | B60: 44941 | C60: C60190 | D60: Phone | E60: 4 | F60: 474.69 | G60: 202 Main St | H60: Gift Card | I60: Cancelled | J60: TRK70857868 | K60: 6 | L60: SAVE10 | M60: Google | N60: 1898.76 | O60: =IF(L60="","No Coupon",L60) -> SAVE10 | P60: =IF(OR(N60<EDA!$H$1,N60>EDA!$H$2),"Outlier","Normal") -> Normal
A61: ORD200059 | B61: 45546 | C61: C97603 | D61: Chair | E61: 4 | F61: 593.27 | G61: 811 Main St | H61: Online | I61: Shipped | J61: TRK47055028 | K61: 5 | M61: Facebook | N61: 2373.08 | O61: =IF(L61="","No Coupon",L61) -> No Coupon | P61: =IF(OR(N61<EDA!$H$1,N61>EDA!$H$2),"Outlier","Normal") -> Normal
A62: ORD200060 | B62: 45525 | C62: C39256 | D62: Desk | E62: 1 | F62: 417.1 | G62: 634 Main St | H62: Debit Card | I62: Returned | J62: TRK23412025 | K62: 3 | L62: FREESHIP | M62: Referral | N62: 417.1 | O62: =IF(L62="","No Coupon",L62) -> FREESHIP | P62: =IF(OR(N62<EDA!$H$1,N62>EDA!$H$2),"Outlier","Normal") -> Normal
A63: ORD200061 | B63: 45375 | C63: C61618 | D63: Desk | E63: 4 | F63: 122.2 | G63: 104 Main St | H63: Cash | I63: Delivered | J63: TRK43458485 | K63: 7 | L63: FREESHIP | M63: Facebook | N63: 488.8 | O63: =IF(L63="","No Coupon",L63) -> FREESHIP | P63: =IF(OR(N63<EDA!$H$1,N63>EDA!$H$2),"Outlier","Normal") -> Normal
A64: ORD200062 | B64: 45160 | C64: C36497 | D64: Desk | E64: 2 | F64: 43.15 | G64: 691 Main St | H64: Debit Card | I64: Pending | J64: TRK12102911 | K64: 3 | L64: WINTER15 | M64: Email | N64: 86.3 | O64: =IF(L64="","No Coupon",L64) -> WINTER15 | P64: =IF(OR(N64<EDA!$H$1,N64>EDA!$H$2),"Outlier","Normal") -> Normal
A65: ORD200063 | B65: 45690 | C65: C96695 | D65: Chair | E65: 1 | F65: 564.86 | G65: 813 Main St | H65: Debit Card | I65: Shipped | J65: TRK64283851 | K65: 6 | L65: WINTER15 | M65: Referral | N65: 564.86 | O65: =IF(L65="","No Coupon",L65) -> WINTER15 | P65: =IF(OR(N65<EDA!$H$1,N65>EDA!$H$2),"Outlier","Normal") -> Normal
A66: ORD200064 | B66: 45833 | C66: C49720 | D66: Printer | E66: 3 | F66: 130.61 | G66: 752 Main St | H66: Debit Card | I66: Cancelled | J66: TRK55785217 | K66: 4 | L66: FREESHIP | M66: Facebook | N66: 391.83 | O66: =IF(L66="","No Coupon",L66) -> FREESHIP | P66: =IF(OR(N66<EDA!$H$1,N66>EDA!$H$2),"Outlier","Normal") -> Normal
A67: ORD200065 | B67: 45290 | C67: C97735 | D67: Monitor | E67: 5 | F67: 81.7 | G67: 385 Main St | H67: Credit Card | I67: Delivered | J67: TRK13743703 | K67: 6 | M67: Instagram | N67: 408.5 | O67: =IF(L67="","No Coupon",L67) -> No Coupon | P67: =IF(OR(N67<EDA!$H$1,N67>EDA!$H$2),"Outlier","Normal") -> Normal
A68: ORD200066 | B68: 45611 | C68: C18104 | D68: Chair | E68: 5 | F68: 127.18 | G68: 715 Main St | H68: Cash | I68: Cancelled | J68: TRK15488568 | K68: 9 | L68: SAVE10 | M68: Referral | N68: 635.9 | O68: =IF(L68="","No Coupon",L68) -> SAVE10 | P68: =IF(OR(N68<EDA!$H$1,N68>EDA!$H$2),"Outlier","Normal") -> Normal
A69: ORD200067 | B69: 45635 | C69: C25587 | D69: Printer | E69: 4 | F69: 12.1 | G69: 440 Main St | H69: Debit Card | I69: Cancelled | J69: TRK55105323 | K69: 8 | M69: Google | N69: 48.4 | O69: =IF(L69="","No Coupon",L69) -> No Coupon | P69: =IF(OR(N69<EDA!$H$1,N69>EDA!$H$2),"Outlier","Normal") -> Normal
A70: ORD200068 | B70: 45271 | C70: C41598 | D70: Chair | E70: 3 | F70: 490.92 | G70: 709 Main St | H70: Credit Card | I70: Pending | J70: TRK81665940 | K70: 5 | L70: FREESHIP | M70: Email | N70: 1472.76 | O70: =IF(L70="","No Coupon",L70) -> FREESHIP | P70: =IF(OR(N70<EDA!$H$1,N70>EDA!$H$2),"Outlier","Normal") -> Normal
A71: ORD200069 | B71: 45057 | C71: C43338 | D71: Monitor | E71: 3 | F71: 478.65 | G71: 552 Main St | H71: Online | I71: Shipped | J71: TRK35241775 | K71: 4 | M71: Referral | N71: 1435.95 | O71: =IF(L71="","No Coupon",L71) -> No Coupon | P71: =IF(OR(N71<EDA!$H$1,N71>EDA!$H$2),"Outlier","Normal") -> Normal
A72: ORD200070 | B72: 45072 | C72: C25123 | D72: Desk | E72: 1 | F72: 629.21 | G72: 384 Main St | H72: Gift Card | I72: Pending | J72: TRK27812282 | K72: 2 | L72: FREESHIP | M72: Instagram | N72: 629.21 | O72: =IF(L72="","No Coupon",L72) -> FREESHIP | P72: =IF(OR(N72<EDA!$H$1,N72>EDA!$H$2),"Outlier","Normal") -> Normal
A73: ORD200071 | B73: 45818 | C73: C37454 | D73: Monitor | E73: 3 | F73: 434.45 | G73: 923 Main St | H73: Credit Card | I73: Pending | J73: TRK28252730 | K73: 4 | M73: Referral | N73: 1303.35 | O73: =IF(L73="","No Coupon",L73) -> No Coupon | P73: =IF(OR(N73<EDA!$H$1,N73>EDA!$H$2),"Outlier","Normal") -> Normal
A74: ORD200072 | B74: 45648 | C74: C19451 | D74: Tablet | E74: 4 | F74: 589.44 | G74: 942 Main St | H74: Gift Card | I74: Returned | J74: TRK87787793 | K74: 5 | M74: Facebook | N74: 2357.76 | O74: =IF(L74="","No Coupon",L74) -> No Coupon | P74: =IF(OR(N74<EDA!$H$1,N74>EDA!$H$2),"Outlier","Normal") -> Normal
A75: ORD200073 | B75: 45049 | C75: C17269 | D75: Monitor | E75: 4 | F75: 433.45 | G75: 129 Main St | H75: Gift Card | I75: Cancelled | J75: TRK79608389 | K75: 4 | M75: Facebook | N75: 1733.8 | O75: =IF(L75="","No Coupon",L75) -> No Coupon | P75: =IF(OR(N75<EDA!$H$1,N75>EDA!$H$2),"Outlier","Normal") -> Normal
A76: ORD200074 | B76: 45101 | C76: C25382 | D76: Phone | E76: 5 | F76: 90.87 | G76: 622 Main St | H76: Cash | I76: Pending | J76: TRK64691287 | K76: 5 | M76: Instagram | N76: 454.35 | O76: =IF(L76="","No Coupon",L76) -> No Coupon | P76: =IF(OR(N76<EDA!$H$1,N76>EDA!$H$2),"Outlier","Normal") -> Normal
A77: ORD200075 | B77: 45195 | C77: C80651 | D77: Tablet | E77: 3 | F77: 398.17 | G77: 917 Main St | H77: Debit Card | I77: Delivered | J77: TRK14846720 | K77: 5 | L77: SAVE10 | M77: Email | N77: 1194.51 | O77: =IF(L77="","No Coupon",L77) -> SAVE10 | P77: =IF(OR(N77<EDA!$H$1,N77>EDA!$H$2),"Outlier","Normal") -> Normal
A78: ORD200076 | B78: 45382 | C78: C58638 | D78: Laptop | E78: 4 | F78: 382.88 | G78: 239 Main St | H78: Cash | I78: Cancelled | J78: TRK38224871 | K78: 6 | L78: WINTER15 | M78: Email | N78: 1531.52 | O78: =IF(L78="","No Coupon",L78) -> WINTER15 | P78: =IF(OR(N78<EDA!$H$1,N78>EDA!$H$2),"Outlier","Normal") -> Normal
A79: ORD200077 | B79: 45436 | C79: C50121 | D79: Phone | E79: 1 | F79: 583.18 | G79: 348 Main St | H79: Credit Card | I79: Returned | J79: TRK79810059 | K79: 5 | M79: Google | N79: 583.18 | O79: =IF(L79="","No Coupon",L79) -> No Coupon | P79: =IF(OR(N79<EDA!$H$1,N79>EDA!$H$2),"Outlier","Normal") -> Normal
A80: ORD200078 | B80: 45510 | C80: C32029 | D80: Printer | E80: 4 | F80: 175.36 | G80: 146 Main St | H80: Debit Card | I80: Delivered | J80: TRK68535532 | K80: 4 | L80: FREESHIP | M80: Instagram | N80: 701.44 | O80: =IF(L80="","No Coupon",L80) -> FREESHIP | P80: =IF(OR(N80<EDA!$H$1,N80>EDA!$H$2),"Outlier","Normal") -> Normal
A81: ORD200079 | B81: 45726 | C81: C76700 | D81: Tablet | E81: 2 | F81: 311.91 | G81: 103 Main St | H81: Online | I81: Shipped | J81: TRK13036341 | K81: 2 | M81: Facebook | N81: 623.82 | O81: =IF(L81="","No Coupon",L81) -> No Coupon | P81: =IF(OR(N81<EDA!$H$1,N81>EDA!$H$2),"Outlier","Normal") -> Normal
A82: ORD200080 | B82: 45104 | C82: C29041 | D82: Phone | E82: 3 | F82: 589.56 | G82: 591 Main St | H82: Online | I82: Returned | J82: TRK28840655 | K82: 6 | M82: Facebook | N82: 1768.68 | O82: =IF(L82="","No Coupon",L82) -> No Coupon | P82: =IF(OR(N82<EDA!$H$1,N82>EDA!$H$2),"Outlier","Normal") -> Normal
A83: ORD200081 | B83: 45085 | C83: C29314 | D83: Monitor | E83: 2 | F83: 394.3 | G83: 496 Main St | H83: Cash | I83: Shipped | J83: TRK59876213 | K83: 6 | L83: FREESHIP | M83: Email | N83: 788.6 | O83: =IF(L83="","No Coupon",L83) -> FREESHIP | P83: =IF(OR(N83<EDA!$H$1,N83>EDA!$H$2),"Outlier","Normal") -> Normal
A84: ORD200082 | B84: 45296 | C84: C65799 | D84: Tablet | E84: 4 | F84: 565.2 | G84: 971 Main St | H84: Debit Card | I84: Shipped | J84: TRK66906607 | K84: 9 | L84: SAVE10 | M84: Google | N84: 2260.8 | O84: =IF(L84="","No Coupon",L84) -> SAVE10 | P84: =IF(OR(N84<EDA!$H$1,N84>EDA!$H$2),"Outlier","Normal") -> Normal
A85: ORD200083 | B85: 45160 | C85: C15681 | D85: Laptop | E85: 4 | F85: 540.41 | G85: 989 Main St | H85: Credit Card | I85: Cancelled | J85: TRK75112172 | K85: 6 | M85: Referral | N85: 2161.64 | O85: =IF(L85="","No Coupon",L85) -> No Coupon | P85: =IF(OR(N85<EDA!$H$1,N85>EDA!$H$2),"Outlier","Normal") -> Normal
A86: ORD200084 | B86: 45166 | C86: C64160 | D86: Monitor | E86: 2 | F86: 165.49 | G86: 967 Main St | H86: Online | I86: Shipped | J86: TRK34121529 | K86: 4 | L86: WINTER15 | M86: Instagram | N86: 330.98 | O86: =IF(L86="","No Coupon",L86) -> WINTER15 | P86: =IF(OR(N86<EDA!$H$1,N86>EDA!$H$2),"Outlier","Normal") -> Normal
A87: ORD200085 | B87: 45544 | C87: C14553 | D87: Tablet | E87: 3 | F87: 146.73 | G87: 768 Main St | H87: Cash | I87: Delivered | J87: TRK93538334 | K87: 8 | L87: FREESHIP | M87: Email | N87: 440.19 | O87: =IF(L87="","No Coupon",L87) -> FREESHIP | P87: =IF(OR(N87<EDA!$H$1,N87>EDA!$H$2),"Outlier","Normal") -> Normal
A88: ORD200086 | B88: 45462 | C88: C88205 | D88: Printer | E88: 5 | F88: 643.03 | G88: 447 Main St | H88: Online | I88: Cancelled | J88: TRK93504166 | K88: 5 | L88: FREESHIP | M88: Referral | N88: 3215.15 | O88: =IF(L88="","No Coupon",L88) -> FREESHIP | P88: =IF(OR(N88<EDA!$H$1,N88>EDA!$H$2),"Outlier","Normal") -> Normal
A89: ORD200087 | B89: 45575 | C89: C91245 | D89: Tablet | E89: 3 | F89: 225.11 | G89: 915 Main St | H89: Cash | I89: Shipped | J89: TRK46976391 | K89: 4 | L89: SAVE10 | M89: Facebook | N89: 675.33 | O89: =IF(L89="","No Coupon",L89) -> SAVE10 | P89: =IF(OR(N89<EDA!$H$1,N89>EDA!$H$2),"Outlier","Normal") -> Normal
A90: ORD200088 | B90: 45813 | C90: C75439 | D90: Desk | E90: 3 | F90: 114.81 | G90: 318 Main St | H90: Gift Card | I90: Cancelled | J90: TRK19831653 | K90: 7 | M90: Google | N90: 344.43 | O90: =IF(L90="","No Coupon",L90) -> No Coupon | P90: =IF(OR(N90<EDA!$H$1,N90>EDA!$H$2),"Outlier","Normal") -> Normal
A91: ORD200089 | B91: 45713 | C91: C17181 | D91: Printer | E91: 5 | F91: 455.33 | G91: 291 Main St | H91: Credit Card | I91: Cancelled | J91: TRK78912978 | K91: 8 | L91: FREESHIP | M91: Google | N91: 2276.65 | O91: =IF(L91="","No Coupon",L91) -> FREESHIP | P91: =IF(OR(N91<EDA!$H$1,N91>EDA!$H$2),"Outlier","Normal") -> Normal
A92: ORD200090 | B92: 45187 | C92: C36540 | D92: Chair | E92: 4 | F92: 182.08 | G92: 611 Main St | H92: Gift Card | I92: Delivered | J92: TRK35828122 | K92: 4 | L92: SAVE10 | M92: Email | N92: 728.32 | O92: =IF(L92="","No Coupon",L92) -> SAVE10 | P92: =IF(OR(N92<EDA!$H$1,N92>EDA!$H$2),"Outlier","Normal") -> Normal
A93: ORD200091 | B93: 45000 | C93: C98216 | D93: Laptop | E93: 5 | F93: 492.75 | G93: 196 Main St | H93: Cash | I93: Shipped | J93: TRK40986666 | K93: 6 | L93: WINTER15 | M93: Referral | N93: 2463.75 | O93: =IF(L93="","No Coupon",L93) -> WINTER15 | P93: =IF(OR(N93<EDA!$H$1,N93>EDA!$H$2),"Outlier","Normal") -> Normal
A94: ORD200092 | B94: 45453 | C94: C29568 | D94: Printer | E94: 4 | F94: 48.61 | G94: 203 Main St | H94: Online | I94: Shipped | J94: TRK46531075 | K94: 7 | L94: FREESHIP | M94: Facebook | N94: 194.44 | O94: =IF(L94="","No Coupon",L94) -> FREESHIP | P94: =IF(OR(N94<EDA!$H$1,N94>EDA!$H$2),"Outlier","Normal") -> Normal
A95: ORD200093 | B95: 44940 | C95: C97262 | D95: Desk | E95: 4 | F95: 431.01 | G95: 837 Main St | H95: Credit Card | I95: Returned | J95: TRK65990229 | K95: 7 | M95: Referral | N95: 1724.04 | O95: =IF(L95="","No Coupon",L95) -> No Coupon | P95: =IF(OR(N95<EDA!$H$1,N95>EDA!$H$2),"Outlier","Normal") -> Normal
A96: ORD200094 | B96: 44968 | C96: C79821 | D96: Chair | E96: 1 | F96: 531.18 | G96: 781 Main St | H96: Gift Card | I96: Returned | J96: TRK12780193 | K96: 6 | L96: WINTER15 | M96: Instagram | N96: 531.18 | O96: =IF(L96="","No Coupon",L96) -> WINTER15 | P96: =IF(OR(N96<EDA!$H$1,N96>EDA!$H$2),"Outlier","Normal") -> Normal
A97: ORD200095 | B97: 45009 | C97: C76761 | D97: Printer | E97: 4 | F97: 117.51 | G97: 839 Main St | H97: Debit Card | I97: Returned | J97: TRK60179774 | K97: 7 | M97: Referral | N97: 470.04 | O97: =IF(L97="","No Coupon",L97) -> No Coupon | P97: =IF(OR(N97<EDA!$H$1,N97>EDA!$H$2),"Outlier","Normal") -> Normal
A98: ORD200096 | B98: 45444 | C98: C93007 | D98: Phone | E98: 2 | F98: 232.83 | G98: 103 Main St | H98: Gift Card | I98: Delivered | J98: TRK85696091 | K98: 7 | M98: Instagram | N98: 465.66 | O98: =IF(L98="","No Coupon",L98) -> No Coupon | P98: =IF(OR(N98<EDA!$H$1,N98>EDA!$H$2),"Outlier","Normal") -> Normal
A99: ORD200097 | B99: 45678 | C99: C15624 | D99: Tablet | E99: 5 | F99: 619.52 | G99: 922 Main St | H99: Debit Card | I99: Pending | J99: TRK40621141 | K99: 9 | M99: Email | N99: 3097.6 | O99: =IF(L99="","No Coupon",L99) -> No Coupon | P99: =IF(OR(N99<EDA!$H$1,N99>EDA!$H$2),"Outlier","Normal") -> Normal
A100: ORD200098 | B100: 44940 | C100: C70921 | D100: Printer | E100: 2 | F100: 228.54 | G100: 533 Main St | H100: Debit Card | I100: Pending | J100: TRK54983109 | K100: 3 | M100: Email | N100: 457.08 | O100: =IF(L100="","No Coupon",L100) -> No Coupon | P100: =IF(OR(N100<EDA!$H$1,N100>EDA!$H$2),"Outlier","Normal") -> Normal
...
